{
  "credit": "Made with Blockbench",
  "texture_size": [
    32,
    32
  ],
  "textures": {
    "0": "fruitbowl:item/abolish_doll",
    "particle": "fruitbowl:item/abolish_doll"
  },
  "elements": [
    {
      "from": [
        5.8,
        6.3,
        5.8
      ],
      "to": [
        10.2,
        10.7,
        10.2
      ],
      "faces": {
        "north": {
          "uv": [
            0.0,
            6.0,
            2.0,
            8.0
          ],
          "texture": "#0"
        },
        "east": {
          "uv": [
            6.5,
            5.5,
            8.5,
            7.5
          ],
          "texture": "#0"
        },
        "south": {
          "uv": [
            7.0,
            0.0,
            9.0,
            2.0
          ],
          "texture": "#0"
        },
        "west": {
          "uv": [
            7.5,
            2.0,
            9.5,
            4.0
          ],
          "texture": "#0"
        },
        "up": {
          "uv": [
            8.5,
            9.5,
            6.5,
            7.5
          ],
          "texture": "#0"
        },
        "down": {
          "uv": [
            2.0,
            8.0,
            0.0,
            10.0
          ],
          "texture": "#0"
        }
      },
      "rotation": {
        "angle": 10,
        "axis": "z",
        "origin": [
          6,
          7,
          6
        ]
      }
    },
    {
      "from": [
        5.9,
        2.9,
        5.9
      ],
      "to": [
        10.1,
        7.1,
        8.1
      ],
      "faces": {
        "north": {
          "uv": [
            2.0,
            8.5,
            4.0,
            10.5
          ],
          "texture": "#0"
        },
        "east": {
          "uv": [
            7.5,
            9.5,
            8.5,
            11.5
          ],
          "texture": "#0"
        },
        "south": {
          "uv": [
            4.0,
            8.5,
            6.0,
            10.5
          ],
          "texture": "#0"
        },
        "west": {
          "uv": [
            8.5,
            10.0,
            9.5,
            12.0
          ],
          "texture": "#0"
        },
        "up": {
          "uv": [
            11.5,
            11.0,
            9.5,
            10.0
          ],
          "texture": "#0"
        },
        "down": {
          "uv": [
            4.0,
            10.5,
            2.0,
            11.5
          ],
          "texture": "#0"
        }
      },
      "rotation": {
        "angle": 12.5,
        "axis": "x",
        "origin": [
          6,
          3,
          6
        ]
      }
    },
    {
      "from": [
        9.5,
        2,
        3
      ],
      "to": [
        11.5,
        4,
        7
      ],
      "faces": {
        "north": {
          "uv": [
            7.5,
            4.0,
            8.5,
            5.0
          ],
          "texture": "#0"
        },
        "east": {
          "uv": [
            10.5,
            3.5,
            12.5,
            4.5
          ],
          "texture": "#0"
        },
        "south": {
          "uv": [
            8.5,
            12.0,
            9.5,
            13.0
          ],
          "texture": "#0"
        },
        "west": {
          "uv": [
            4.0,
            10.5,
            6.0,
            11.5
          ],
          "texture": "#0"
        },
        "up": {
          "uv": [
            11.5,
            6.5,
            10.5,
            4.5
          ],
          "texture": "#0"
        },
        "down": {
          "uv": [
            11.5,
            6.5,
            10.5,
            8.5
          ],
          "texture": "#0"
        }
      },
      "rotation": {
        "angle": -20,
        "axis": "y",
        "origin": [
          9,
          2,
          3
        ]
      }
    },
    {
      "from": [
        4.5,
        2,
        4
      ],
      "to": [
        6.5,
        4,
        8
      ],
      "faces": {
        "north": {
          "uv": [
            12.5,
            3.0,
            13.5,
            4.0
          ],
          "texture": "#0"
        },
        "east": {
          "uv": [
            10.5,
            8.5,
            12.5,
            9.5
          ],
          "texture": "#0"
        },
        "south": {
          "uv": [
            12.5,
            4.0,
            13.5,
            5.0
          ],
          "texture": "#0"
        },
        "west": {
          "uv": [
            11.0,
            0.0,
            13.0,
            1.0
          ],
          "texture": "#0"
        },
        "up": {
          "uv": [
            10.5,
            13.0,
            9.5,
            11.0
          ],
          "texture": "#0"
        },
        "down": {
          "uv": [
            11.5,
            11.0,
            10.5,
            13.0
          ],
          "texture": "#0"
        }
      },
      "rotation": {
        "angle": 20,
        "axis": "y",
        "origin": [
          5,
          2,
          4
        ]
      }
    },
    {
      "from": [
        3,
        3.5,
        6.7
      ],
      "to": [
        5,
        7.5,
        8.7
      ],
      "faces": {
        "north": {
          "uv": [
            0.0,
            11.5,
            1.0,
            13.5
          ],
          "texture": "#0"
        },
        "east": {
          "uv": [
            1.0,
            11.5,
            2.0,
            13.5
          ],
          "texture": "#0"
        },
        "south": {
          "uv": [
            11.5,
            1.0,
            12.5,
            3.0
          ],
          "texture": "#0"
        },
        "west": {
          "uv": [
            2.0,
            11.5,
            3.0,
            13.5
          ],
          "texture": "#0"
        },
        "up": {
          "uv": [
            13.5,
            6.0,
            12.5,
            5.0
          ],
          "texture": "#0"
        },
        "down": {
          "uv": [
            13.5,
            6.0,
            12.5,
            7.0
          ],
          "texture": "#0"
        }
      },
      "rotation": {
        "angle": -35,
        "axis": "z",
        "origin": [
          3,
          3,
          8
        ]
      }
    },
    {
      "from": [
        11,
        3.5,
        6.7
      ],
      "to": [
        13,
        7.5,
        8.7
      ],
      "faces": {
        "north": {
          "uv": [
            3.0,
            11.5,
            4.0,
            13.5
          ],
          "texture": "#0"
        },
        "east": {
          "uv": [
            4.0,
            11.5,
            5.0,
            13.5
          ],
          "texture": "#0"
        },
        "south": {
          "uv": [
            11.5,
            4.5,
            12.5,
            6.5
          ],
          "texture": "#0"
        },
        "west": {
          "uv": [
            5.0,
            11.5,
            6.0,
            13.5
          ],
          "texture": "#0"
        },
        "up": {
          "uv": [
            13.5,
            8.0,
            12.5,
            7.0
          ],
          "texture": "#0"
        },
        "down": {
          "uv": [
            13.5,
            8.0,
            12.5,
            9.0
          ],
          "texture": "#0"
        }
      },
      "rotation": {
        "angle": 35,
        "axis": "z",
        "origin": [
          13,
          3,
          8
        ]
      }
    },
    {
      "from": [
        5.95,
        6.2,
        5.7
      ],
      "to": [
        10.55,
        9.8,
        6.3
      ],
      "faces": {
        "north": {
          "uv": [
            0.0,
            0.0,
            3.5,
            3.0
          ],
          "texture": "#0"
        },
        "east": {
          "uv": [
            3.5,
            5.5,
            5.0,
            8.5
          ],
          "texture": "#0"
        },
        "south": {
          "uv": [
            0.0,
            3.0,
            3.5,
            6.0
          ],
          "texture": "#0"
        },
        "west": {
          "uv": [
            5.0,
            5.5,
            6.5,
            8.5
          ],
          "texture": "#0"
        },
        "up": {
          "uv": [
            7.0,
            1.5,
            3.5,
            0.0
          ],
          "texture": "#0"
        },
        "down": {
          "uv": [
            7.0,
            1.5,
            3.5,
            3.0
          ],
          "texture": "#0"
        }
      },
      "rotation": {
        "angle": 10,
        "axis": "z",
        "origin": [
          0,
          5,
          4.5
        ]
      }
    },
    {
      "from": [
        7.2,
        4.7,
        5.95
      ],
      "to": [
        8.8,
        7.3,
        6.55
      ],
      "faces": {
        "north": {
          "uv": [
            3.5,
            3.0,
            5.5,
            5.5
          ],
          "texture": "#0"
        },
        "east": {
          "uv": [
            2.0,
            6.0,
            3.5,
            8.5
          ],
          "texture": "#0"
        },
        "south": {
          "uv": [
            5.5,
            3.0,
            7.5,
            5.5
          ],
          "texture": "#0"
        },
        "west": {
          "uv": [
            6.0,
            9.5,
            7.5,
            12.0
          ],
          "texture": "#0"
        },
        "up": {
          "uv": [
            11.5,
            3.5,
            9.5,
            2.0
          ],
          "texture": "#0"
        },
        "down": {
          "uv": [
            2.0,
            10.0,
            0.0,
            11.5
          ],
          "texture": "#0"
        }
      },
      "rotation": {
        "angle": 12.5,
        "axis": "x",
        "origin": [
          1.25,
          3.5,
          4.75
        ]
      }
    },
    {
      "from": [
        5.6,
        7.65,
        6.65
      ],
      "to": [
        6.3,
        8.35,
        7.35
      ],
      "faces": {
        "north": {
          "uv": [
            12.5,
            11.5,
            13.5,
            12.5
          ],
          "texture": "#0"
        },
        "east": {
          "uv": [
            12.5,
            12.5,
            13.5,
            13.5
          ],
          "texture": "#0"
        },
        "south": {
          "uv": [
            13.0,
            0.0,
            14.0,
            1.0
          ],
          "texture": "#0"
        },
        "west": {
          "uv": [
            8.5,
            13.0,
            9.5,
            14.0
          ],
          "texture": "#0"
        },
        "up": {
          "uv": [
            10.5,
            14.0,
            9.5,
            13.0
          ],
          "texture": "#0"
        },
        "down": {
          "uv": [
            11.5,
            13.0,
            10.5,
            14.0
          ],
          "texture": "#0"
        }
      },
      "rotation": {
        "angle": 10,
        "axis": "z",
        "origin": [
          5,
          7,
          6
        ]
      }
    },
    {
      "from": [
        9.0,
        6.25,
        6.35
      ],
      "to": [
        9.5,
        6.75,
        6.85
      ],
      "faces": {
        "north": {
          "uv": [
            0.0,
            13.5,
            1.0,
            14.5
          ],
          "texture": "#0"
        },
        "east": {
          "uv": [
            1.0,
            13.5,
            2.0,
            14.5
          ],
          "texture": "#0"
        },
        "south": {
          "uv": [
            2.0,
            13.5,
            3.0,
            14.5
          ],
          "texture": "#0"
        },
        "west": {
          "uv": [
            3.0,
            13.5,
            4.0,
            14.5
          ],
          "texture": "#0"
        },
        "up": {
          "uv": [
            14.5,
            4.0,
            13.5,
            3.0
          ],
          "texture": "#0"
        },
        "down": {
          "uv": [
            5.0,
            13.5,
            4.0,
            14.5
          ],
          "texture": "#0"
        }
      },
      "rotation": {
        "angle": 12.5,
        "axis": "x",
        "origin": [
          8.25,
          5.5,
          5.5
        ]
      }
    },
    {
      "from": [
        9.0,
        4.75,
        6.0
      ],
      "to": [
        9.5,
        5.25,
        6.5
      ],
      "faces": {
        "north": {
          "uv": [
            13.5,
            4.0,
            14.5,
            5.0
          ],
          "texture": "#0"
        },
        "east": {
          "uv": [
            5.0,
            13.5,
            6.0,
            14.5
          ],
          "texture": "#0"
        },
        "south": {
          "uv": [
            13.5,
            5.0,
            14.5,
            6.0
          ],
          "texture": "#0"
        },
        "west": {
          "uv": [
            13.5,
            6.0,
            14.5,
            7.0
          ],
          "texture": "#0"
        },
        "up": {
          "uv": [
            8.0,
            14.5,
            7.0,
            13.5
          ],
          "texture": "#0"
        },
        "down": {
          "uv": [
            14.5,
            7.0,
            13.5,
            8.0
          ],
          "texture": "#0"
        }
      },
      "rotation": {
        "angle": 12.5,
        "axis": "x",
        "origin": [
          8.25,
          4,
          5.25
        ]
      }
    },
    {
      "from": [
        3.15,
        3.4,
        6.65
      ],
      "to": [
        5.35,
        4.6,
        8.85
      ],
      "faces": {
        "north": {
          "uv": [
            7.5,
            5.0,
            8.5,
            5.5
          ],
          "texture": "#0"
        },
        "east": {
          "uv": [
            9.5,
            3.5,
            10.5,
            4.0
          ],
          "texture": "#0"
        },
        "south": {
          "uv": [
            10.5,
            9.5,
            11.5,
            10.0
          ],
          "texture": "#0"
        },
        "west": {
          "uv": [
            11.5,
            3.0,
            12.5,
            3.5
          ],
          "texture": "#0"
        },
        "up": {
          "uv": [
            14.5,
            9.0,
            13.5,
            8.0
          ],
          "texture": "#0"
        },
        "down": {
          "uv": [
            14.5,
            9.0,
            13.5,
            10.0
          ],
          "texture": "#0"
        }
      },
      "rotation": {
        "angle": -35,
        "axis": "z",
        "origin": [
          3.25,
          3.5,
          6.75
        ]
      }
    },
    {
      "from": [
        10.9,
        2.15,
        6.65
      ],
      "to": [
        13.1,
        3.35,
        8.85
      ],
      "faces": {
        "north": {
          "uv": [
            12.5,
            9.0,
            13.5,
            9.5
          ],
          "texture": "#0"
        },
        "east": {
          "uv": [
            11.5,
            13.5,
            12.5,
            14.0
          ],
          "texture": "#0"
        },
        "south": {
          "uv": [
            13.5,
            12.0,
            14.5,
            12.5
          ],
          "texture": "#0"
        },
        "west": {
          "uv": [
            12.5,
            13.5,
            13.5,
            14.0
          ],
          "texture": "#0"
        },
        "up": {
          "uv": [
            14.5,
            11.0,
            13.5,
            10.0
          ],
          "texture": "#0"
        },
        "down": {
          "uv": [
            14.5,
            11.0,
            13.5,
            12.0
          ],
          "texture": "#0"
        }
      },
      "rotation": {
        "angle": 35,
        "axis": "z",
        "origin": [
          11,
          2.25,
          6.75
        ]
      }
    },
    {
      "from": [
        9.45,
        1.95,
        3.45
      ],
      "to": [
        11.75,
        4.05,
        4.05
      ],
      "faces": {
        "north": {
          "uv": [
            8.5,
            4.0,
            10.5,
            6.0
          ],
          "texture": "#0"
        },
        "east": {
          "uv": [
            11.5,
            6.5,
            12.5,
            8.5
          ],
          "texture": "#0"
        },
        "south": {
          "uv": [
            8.5,
            6.0,
            10.5,
            8.0
          ],
          "texture": "#0"
        },
        "west": {
          "uv": [
            7.5,
            11.5,
            8.5,
            13.5
          ],
          "texture": "#0"
        },
        "up": {
          "uv": [
            13.5,
            10.5,
            11.5,
            9.5
          ],
          "texture": "#0"
        },
        "down": {
          "uv": [
            13.5,
            10.5,
            11.5,
            11.5
          ],
          "texture": "#0"
        }
      },
      "rotation": {
        "angle": -20,
        "axis": "y",
        "origin": [
          8.75,
          3.25,
          2.75
        ]
      }
    },
    {
      "from": [
        4.45,
        1.95,
        5.2
      ],
      "to": [
        6.75,
        4.05,
        5.8
      ],
      "faces": {
        "north": {
          "uv": [
            8.5,
            8.0,
            10.5,
            10.0
          ],
          "texture": "#0"
        },
        "east": {
          "uv": [
            11.5,
            11.5,
            12.5,
            13.5
          ],
          "texture": "#0"
        },
        "south": {
          "uv": [
            9.0,
            0.0,
            11.0,
            2.0
          ],
          "texture": "#0"
        },
        "west": {
          "uv": [
            6.0,
            12.0,
            7.0,
            14.0
          ],
          "texture": "#0"
        },
        "up": {
          "uv": [
            14.5,
            2.0,
            12.5,
            1.0
          ],
          "texture": "#0"
        },
        "down": {
          "uv": [
            14.5,
            2.0,
            12.5,
            3.0
          ],
          "texture": "#0"
        }
      },
      "rotation": {
        "angle": 20,
        "axis": "y",
        "origin": [
          3.75,
          3.25,
          4.5
        ]
      }
    }
  ],
  "display": {
    "thirdperson_righthand": {
      "rotation": [
        32.6,
        29.96,
        4.36
      ]
    },
    "thirdperson_lefthand": {
      "rotation": [
        71.73,
        -1.59,
        -20.74
      ],
      "translation": [
        2.75,
        -1.25,
        15.75
      ]
    },
    "firstperson_righthand": {
      "translation": [
        0,
        1.25,
        0
      ],
      "scale": [
        0.5,
        0.5,
        0.5
      ]
    },
    "firstperson_lefthand": {
      "translation": [
        0,
        1.25,
        0
      ],
      "scale": [
        0.5,
        0.5,
        0.5
      ]
    },
    "ground": {
      "translation": [
        0,
        3.25,
        0
      ]
    },
    "gui": {
      "rotation": [
        -180,
        44.25,
        -180
      ]
    },
    "head": {
      "translation": [
        0,
        15.5,
        0.75
      ],
      "scale": [
        1.5,
        1.5,
        1.5
      ]
    },
    "fixed": {
      "rotation": [
        -90,
        0,
        0
      ],
      "translation": [
        0,
        0,
        -12
      ],
      "scale": [
        2,
        2,
        2
      ]
    },
    "on_shelf": {
      "rotation": [
        0,
        -180,
        0
      ],
      "scale": [
        2,
        2,
        2
      ]
    }
  }
}
